kolona/__init__.py
kolona/constants.py
kolona/exceptions.py
kolona/logger.py
kolona/task.py
kolona/workers.py
kolona-0.2.1.dist-info/LICENSE
kolona-0.2.1.dist-info/METADATA
kolona-0.2.1.dist-info/WHEEL
kolona-0.2.1.dist-info/top_level.txt
kolona-0.2.1.dist-info/RECORD
