Metadata-Version: 2.1
Name: kolona
Version: 0.2.1
Summary: A minimalistic in-memory async Python Task queue
Home-page: https://github.com/roks0n/kolona/
Author: roks0n
Maintainer: roks0n
License: MIT
Keywords: queue,task queue,memory
Classifier: Programming Language :: Python :: 3
Requires-Python: >=3.8
License-File: LICENSE
